selfplay/__init__.py
selfplay/chatbot.py
selfplay-0.1.0.dist-info/LICENSE
selfplay-0.1.0.dist-info/METADATA
selfplay-0.1.0.dist-info/WHEEL
selfplay-0.1.0.dist-info/entry_points.txt
selfplay-0.1.0.dist-info/top_level.txt
selfplay-0.1.0.dist-info/RECORD
