Metadata-Version: 2.1
Name: selfplay
Version: 0.1.0
Summary: A multi-bot simulation package with multi-turn conversation and self-play and role-play capabilities
Home-page: https://github.com/prdeepakbabu
Author: Deepak Babu Piskala
Author-email: prdeepak.babu@gmail.com
Classifier: Programming Language :: Python :: 3
Classifier: License :: OSI Approved :: MIT License
Classifier: Operating System :: OS Independent
Requires-Python: >=3.7
License-File: LICENSE
Requires-Dist: openai
Requires-Dist: markdown2
Requires-Dist: requests
Requires-Dist: pyyaml
